tests/__init__.py
tests/test_client.py
tests/test_server.py
tests/test_vad.py
whisper_live/__init__.py
whisper_live/__version__.py
whisper_live/client.py
whisper_live/server.py
whisper_live/utils.py
whisper_live/vad.py
whisper_live/backend/__init__.py
whisper_live/backend/base.py
whisper_live/backend/faster_whisper_backend.py
whisper_live/backend/openvino_backend.py
whisper_live/backend/trt_backend.py
whisper_live/transcriber/__init__.py
whisper_live/transcriber/tensorrt_utils.py
whisper_live/transcriber/transcriber_faster_whisper.py
whisper_live/transcriber/transcriber_openvino.py
whisper_live/transcriber/transcriber_tensorrt.py
whisper_live-0.7.1.dist-info/LICENSE
whisper_live-0.7.1.dist-info/METADATA
whisper_live-0.7.1.dist-info/WHEEL
whisper_live-0.7.1.dist-info/top_level.txt
whisper_live-0.7.1.dist-info/RECORD
