Metadata-Version: 2.1
Name: whisper-live
Version: 0.7.1
Summary: A nearly-live implementation of OpenAI's Whisper.
Home-page: https://github.com/collabora/WhisperLive
Author: Collabora Ltd
Author-email: vineet.suryan@collabora.com
License: MIT
Platform: UNKNOWN
Classifier: Development Status :: 4 - Beta
Classifier: Intended Audience :: Developers
Classifier: Intended Audience :: Science/Research
Classifier: License :: OSI Approved :: MIT License
Classifier: Programming Language :: Python :: 3
Classifier: Programming Language :: Python :: 3 :: Only
Classifier: Programming Language :: Python :: 3.8
Classifier: Programming Language :: Python :: 3.9
Classifier: Topic :: Scientific/Engineering :: Artificial Intelligence
Requires-Python: >=3.9
License-File: LICENSE
Requires-Dist: PyAudio
Requires-Dist: faster-whisper==1.1.0
Requires-Dist: torch
Requires-Dist: torchaudio
Requires-Dist: websockets
Requires-Dist: onnxruntime==1.17.0
Requires-Dist: scipy
Requires-Dist: websocket-client
Requires-Dist: numba
Requires-Dist: openai-whisper==20240930
Requires-Dist: kaldialign
Requires-Dist: soundfile
Requires-Dist: tokenizers==0.20.3
Requires-Dist: librosa
Requires-Dist: numpy==1.26.4
Requires-Dist: openvino
Requires-Dist: openvino-genai
Requires-Dist: openvino-tokenizers
Requires-Dist: optimum
Requires-Dist: optimum-intel
